cartorio/__init__.py
cartorio/log.py
cartorio/conf/logging.conf
cartorio-3.0.0.dist-info/LICENSE
cartorio-3.0.0.dist-info/METADATA
cartorio-3.0.0.dist-info/WHEEL
cartorio-3.0.0.dist-info/entry_points.txt
cartorio-3.0.0.dist-info/top_level.txt
cartorio-3.0.0.dist-info/RECORD
