Metadata-Version: 2.1
Name: cartorio
Version: 3.0.0
Summary: Cartorio: A library for logging
Home-page: https://github.com/hsteinshiromoto/cartorio
Author: Humberto STEIN SHIROMOTO
Author-email: h.stein.shiromoto@gmail.com
License: MIT
Platform: UNKNOWN
Classifier: License :: OSI Approved :: MIT License
Classifier: Programming Language :: Python :: 3
Classifier: Programming Language :: Python :: 3.9
